krovetz/wrapped.cpython-36m-x86_64-linux-gnu.so
krovetz/__init__.py
krovetz-1.0.2.dist-info/LICENSE.txt
krovetz-1.0.2.dist-info/WHEEL
krovetz-1.0.2.dist-info/top_level.txt
krovetz-1.0.2.dist-info/METADATA
krovetz-1.0.2.dist-info/RECORD
