Metadata-Version: 2.1
Name: krovetz
Version: 1.0.2
Summary: Krovetz Stemmer
Home-page: http://github.com/ptorrestr/py_krovetz
Author: Pablo Torres
Author-email: pablo.torres.t@gmail.com
License: MIT
Platform: UNKNOWN
Classifier: Programming Language :: Python :: 3.6
Classifier: Programming Language :: C++
